[{
    "name": "طاجن ملوخية","price": 40,"image": "1.jpg","category": "c"},
    {"name": "دجاجة بدون ارز","price": 270,"image": "2.jpg","category": "m"},    
    {"name": "طاجن بطاطس باللحمة","price": 195,"image": "3.jpg","category": "c"},
    {"name": "طاجن بامية باللحمة","price": 200,"image": "4.jpg","category": "c"},
    {"name": "شوربة لسان عصفور","price": 20,"image": "5.jpg","category": "a"},   
    {"name": "مياه معدنية","price": 10,"image": "6.jpg","category": "d"},        
    {"name": "حمام مشوي","price": 130,"image": "7.jpg","category": "m"},
    {"name": "كيلو كفتة","price": 500,"image": "8.jpg","category": "m"},
    {"name": "ارز كبسة","price": 15,"image": "9.jpg","category": "m"},
    {"name": "ورق عنب","price": 50,"image": "10.jpg","category": "a"},
    {"name": "سلطة خضراء","price": 20,"image": "11.jpg","category": "a"},
    {"name": "سلطة طحينة","price": 15,"image": "12.jpg","category": "a"},
    {"name": "نصف دجاجة","price": 155,"image": "13.jpg","category": "m"},
    {"name": "ربع دجاجة","price": 85,"image": "14.jpg","category": "m"},
    {"name": "نص كفتة","price": 220,"image": "8.jpg","category": "m"},
    {"name": "ربع كفتة","price": 120,"image": "8.jpg","category": "m"},
    {"name": "محاشي (مشكل)","price": 75,"image": "17.png","category": "m"},
    {"name": "ممبار","price": 73,"image": "18.png","category": "m"},
    {"name": "كيلو محاشي ","price": 230,"image": "17.png","category": "m"},
    {"name": "كيلو ممبار","price": 230,"image": "18.png","category": "m"},
    {"name": "شيش طاووق","price": 520,"image": "21.jpg","category": "m"},
    {"name": "بطاطس فرم","price": 15,"image": "22.jpg","category": "a"}
]
